jupyter_compare_view/__init__.py
jupyter_compare_view/compare.py
jupyter_compare_view/sw_cellmagic.py
jupyter_compare_view/template.html
vendor/compare_view/browser_compare_view.js
jupyter_compare_view-0.2.4.dist-info/LICENSE
jupyter_compare_view-0.2.4.dist-info/METADATA
jupyter_compare_view-0.2.4.dist-info/WHEEL
jupyter_compare_view-0.2.4.dist-info/RECORD
