Metadata-Version: 2.1
Name: jupyter-compare-view
Version: 0.2.4
Summary: Blend Between Multiple Images in JupyterLab.
License: MIT
Author: Octoframes
Requires-Python: >=3.8,<3.13
Classifier: License :: OSI Approved :: MIT License
Classifier: Programming Language :: Python :: 3
Classifier: Programming Language :: Python :: 3.8
Classifier: Programming Language :: Python :: 3.9
Classifier: Programming Language :: Python :: 3.10
Classifier: Programming Language :: Python :: 3.11
Requires-Dist: Jinja2 (>=2.11.3)
Requires-Dist: Pillow (>=7.1.2)
Requires-Dist: ipykernel (>=5.0.0)
Requires-Dist: ipython (>=6.0.0)
